{"exam":{"name":"求实园1-202(计算机应用4)教室：14：30—15：10","id":"0373bf4e-c189-449a-913c-e8fab8863739","startAt":1610433000000,"endAt":1610435400000,"usage":true,"createdAt":"2021-01-05T15:15:15.000Z","updatedAt":"2021-01-05T15:15:15.000Z","PaperId":"b3c972cc-fe33-4262-9e20-e492c2fb1f66"},"paper":{"trueFalse":[{"id":"307ff785557af42a648ec6955714f646","title":"人类实践的基本形式包含精神活动。（ ）","detail":"{\"A\":\"正确\",\"B\":\"错误\",\"C\":\"undefined\",\"D\":\"undefined\"}","difficult":"中","type":"trueFalse","chapter":"30eeedcc-48cd-4c0d-acb8-c392443ad937"},{"id":"8559be671b58d85740b4e842074b4a1d","title":"在认识活动中起决定作用的是认识主体的能力水平。（ ）","detail":"{\"A\":\"正确\",\"B\":\"错误\",\"C\":\"undefined\",\"D\":\"undefined\"}","difficult":"中","type":"trueFalse","chapter":"30eeedcc-48cd-4c0d-acb8-c392443ad937"},{"id":"726d38b313d37922347b7048cf68baa5","title":"“感觉到了的东西，我们不能立刻理解它，只有理解了的东西，才能更深刻地感觉它”，这一观点说明通过感性认识能够把握事物的本质。（ ）","detail":"{\"A\":\"正确\",\"B\":\"错误\",\"C\":\"undefined\",\"D\":\"undefined\"}","difficult":"易","type":"trueFalse","chapter":"30eeedcc-48cd-4c0d-acb8-c392443ad937"},{"id":"619e0d3819d9255294f2fb08d947d970","title":"人文社会科学的实验活动也是科学实验。（ ）","detail":"{\"A\":\"正确\",\"B\":\"错误\",\"C\":\"undefined\",\"D\":\"undefined\"}","difficult":"易","type":"trueFalse","chapter":"b2f7442d-f018-4535-bced-bcd48b6021fb"},{"id":"82bce0372995bcac0fa3848151d1224f","title":"人们不能自由选择某一社会形态。（ ）","detail":"{\"A\":\"正确\",\"B\":\"错误\",\"C\":\"undefined\",\"D\":\"undefined\"}","difficult":"易","type":"trueFalse","chapter":"b2f7442d-f018-4535-bced-bcd48b6021fb"},{"id":"8182b68f6784b92ece83f140d7b10e06","title":"在人们的历史活动中，谋事在人，成事在天。（ ）","detail":"{\"A\":\"正确\",\"B\":\"错误\",\"C\":\"undefined\",\"D\":\"undefined\"}","difficult":"难","type":"trueFalse","chapter":"b2f7442d-f018-4535-bced-bcd48b6021fb"},{"id":"edc18b89e98eeb62e8d91ed0984edbd0","title":"科学社会主义一般原则是社会主义事业发展规律的集中体现,是马克思主义政党领导人民进行社会主义革命、建设、改革的基本遵循。（  ）","detail":"{\"A\":\"正确\",\"B\":\"错误\",\"C\":\"undefined\",\"D\":\"undefined\"}","difficult":"中","type":"trueFalse","chapter":"684a7593-74e4-4d89-a272-a0a1c1fedd0e"},{"id":"9b0f0a9ba46f7d925a63d03327efe5d7","title":"空想社会主义是科学社会主义的直接思想来源。 （  ）","detail":"{\"A\":\"正确\",\"B\":\"错误\",\"C\":\"undefined\",\"D\":\"undefined\"}","difficult":"易","type":"trueFalse","chapter":"684a7593-74e4-4d89-a272-a0a1c1fedd0e"},{"id":"e407704dee09e65c134125984e09e577","title":"科学社会主义创立的理论基础是唯物史观和剩余价值学说。（  ）","detail":"{\"A\":\"正确\",\"B\":\"错误\",\"C\":\"undefined\",\"D\":\"undefined\"}","difficult":"易","type":"trueFalse","chapter":"684a7593-74e4-4d89-a272-a0a1c1fedd0e"},{"id":"3aed098923a4f100bd02d73000eb73f3","title":"随着科学技术的发展，人类已经制造出诸如醋酸纤维、聚苯乙烯、合成橡胶等自然界原本不存在的化合物，其数量已经达到数百万种。这说明物质世界是人类创造的。（ ）","detail":"{\"A\":\"正确\",\"B\":\"错误\",\"C\":\"undefined\",\"D\":\"undefined\"}","difficult":"中","type":"trueFalse","chapter":"e67f971e-8d43-4ee2-acf1-30ee30aa0119"},{"id":"3f76d167edf0be03cfc2438feb1d11df","title":"语言的产生使人从统一的自然界中分化出来。（ ）","detail":"{\"A\":\"正确\",\"B\":\"错误\",\"C\":\"undefined\",\"D\":\"undefined\"}","difficult":"中","type":"trueFalse","chapter":"e67f971e-8d43-4ee2-acf1-30ee30aa0119"},{"id":"45162580f839781fc21f094e659de7a6","title":"“只要知道自然界一切组成部分的相对位置和全部作用，一亿年以后的状况，都可以精确无误地演算出来，因为未来的一切早就在宇宙诞生时便已完全确定了”。这是机械决定论。（ ）","detail":"{\"A\":\"正确\",\"B\":\"错误\",\"C\":\"undefined\",\"D\":\"undefined\"}","difficult":"中","type":"trueFalse","chapter":"e67f971e-8d43-4ee2-acf1-30ee30aa0119"},{"id":"0d0ba26ac076bfdca12726e078a26daa","title":"马克思主义最重要的理论品质是创新。（ ）","detail":"{\"A\":\"正确\",\"B\":\"错误\",\"C\":\"undefined\",\"D\":\"undefined\"}","difficult":"中","type":"trueFalse","chapter":"c32b6b23-286f-41c8-a871-9e6fa875baba"},{"id":"82e05d0efd6592f94d6f19369e23ff37","title":"马克思主义诞生于18世纪。（ ）","detail":"{\"A\":\"正确\",\"B\":\"错误\",\"C\":\"undefined\",\"D\":\"undefined\"}","difficult":"易","type":"trueFalse","chapter":"c32b6b23-286f-41c8-a871-9e6fa875baba"},{"id":"ddc48d4d7a7f7ac9bbb79ae8972de809","title":"毛泽东思想属于中国特色社会主义理论体系。（ ）","detail":"{\"A\":\"正确\",\"B\":\"错误\",\"C\":\"undefined\",\"D\":\"undefined\"}","difficult":"难","type":"trueFalse","chapter":"c32b6b23-286f-41c8-a871-9e6fa875baba"},{"id":"f1ea2d37fc0e68b0b9da58ac3f61c15a","title":"生产剩余价值是资本主义生产方式的绝对规律。 (  )","detail":"{\"A\":\"正确\",\"B\":\"错误\",\"C\":\"undefined\",\"D\":\"undefined\"}","difficult":"易","type":"trueFalse","chapter":"c6b67cc9-950a-43a5-9643-80a16fbe6b09"},{"id":"37223cd74a61757d5c4c628b5da6d804","title":"可变资本在生产过程中不发生增殖。(  )","detail":"{\"A\":\"正确\",\"B\":\"错误\",\"C\":\"undefined\",\"D\":\"undefined\"}","difficult":"中","type":"trueFalse","chapter":"c6b67cc9-950a-43a5-9643-80a16fbe6b09"},{"id":"f341bbea1f9b1b8aff37261be2c68f24","title":"生产物质资料的劳动过程必需具备的三个基本要素是劳动者、劳动对象、劳动资料。(  )","detail":"{\"A\":\"正确\",\"B\":\"错误\",\"C\":\"undefined\",\"D\":\"undefined\"}","difficult":"中","type":"trueFalse","chapter":"c6b67cc9-950a-43a5-9643-80a16fbe6b09"},{"id":"26bb295c541717abe03fbc673fea85ac","title":"共产主义理想是能够实现的社会理想，因为这一社会理想具有客观必然性，经过努力可以实现。（）","detail":"{\"A\":\"正确\",\"B\":\"错误\",\"C\":\"undefined\",\"D\":\"undefined\"}","difficult":"中","type":"trueFalse","chapter":"60b92b95-8392-4eae-93ec-d774d90701d7"},{"id":"37052140284b0c7aee73519f2690787e","title":"无产阶级专政的最终目标是消灭资产阶级。（）","detail":"{\"A\":\"正确\",\"B\":\"错误\",\"C\":\"undefined\",\"D\":\"undefined\"}","difficult":"中","type":"trueFalse","chapter":"60b92b95-8392-4eae-93ec-d774d90701d7"}],"single":[{"id":"08620919e8c40770badbf2cff25d8ff4","title":"（ ），标志着现代无产阶级作为独立的政治力量已经登上了历史舞台。","detail":"{\"A\":\"法国七月革命\",\"B\":\"英国议会改革\",\"C\":\"法国、英国、德国的三大起义\",\"D\":\"巴黎公社\"}","difficult":"易","type":"single","chapter":"c32b6b23-286f-41c8-a871-9e6fa875baba"},{"id":"450475437015d929b8e0d76640841a45","title":"马克思主义是（ ）思想的科学体系。","detail":"{\"A\":\"农民阶级\",\"B\":\"地主阶级\",\"C\":\"资产阶级\",\"D\":\"无产阶级\"}","difficult":"易","type":"single","chapter":"c32b6b23-286f-41c8-a871-9e6fa875baba"},{"id":"78e48fd4fa5e272b5d1c4f9b1257423c","title":"马克思主义最崇高的社会理想：（ ）。","detail":"{\"A\":\"实现共产主义\",\"B\":\"消灭阶级、消灭国家\",\"C\":\"实现个人的绝对自由\",\"D\":\"实现人权\"}","difficult":"易","type":"single","chapter":"c32b6b23-286f-41c8-a871-9e6fa875baba"},{"id":"7b7b4c8542b578d5aab70a92d7656a84","title":"（ ）是马克思主义中国化最新理论成果。","detail":"{\"A\":\"习近平新时代中国特色社会主义思想\",\"B\":\"科学发展观\",\"C\":\"“三个代表”重要思想\",\"D\":\"邓小平理论\"}","difficult":"易","type":"single","chapter":"c32b6b23-286f-41c8-a871-9e6fa875baba"},{"id":"84d1f0d399d7662cfa1fd9d8eda49e4e","title":"（ ）的发展为马克思主义的产生提供了经济、社会历史条件。","detail":"{\"A\":\"空想社会主义\",\"B\":\"商品经济\",\"C\":\"小农经济\",\"D\":\"资本主义经济\"}","difficult":"易","type":"single","chapter":"c32b6b23-286f-41c8-a871-9e6fa875baba"},{"id":"ac7ddc4b9527fa537b199e01fd6e194b","title":"整个马克思主义学说的理论基础是（ ）。","detail":"{\"A\":\"马克思主义哲学\",\"B\":\"马克思主义政治经济学\",\"C\":\"科学社会主义学说\",\"D\":\"阶级和阶级斗争学说\"}","difficult":"易","type":"single","chapter":"c32b6b23-286f-41c8-a871-9e6fa875baba"},{"id":"ae6e834e768ded07330d89f23b72e0ce","title":"在（ ）的指引下，中国共产党团结带领广大人民取得了新民主主义革命的伟大胜利。","detail":"{\"A\":\"毛泽东思想\",\"B\":\"邓小平理论\",\"C\":\"“三个代表”重要思想\",\"D\":\"科学发展观\"}","difficult":"易","type":"single","chapter":"c32b6b23-286f-41c8-a871-9e6fa875baba"},{"id":"cdd7988790ca39de10ce9a731b848084","title":"马克思主义哲学的创立意味着：（ ）。","detail":"{\"A\":\"绝对真理体系的创立\",\"B\":\"人类优秀哲学思想的继承和在更高阶段上发展的起点\",\"C\":\"人类哲学思想的发展达到顶峰\",\"D\":\"科学哲学体系的最终完成\"}","difficult":"中","type":"single","chapter":"c32b6b23-286f-41c8-a871-9e6fa875baba"},{"id":"c3cf85a595bd94db327addbc71e9b3a2","title":"唯物史观认为，人类的第一个历史活动是：（ ）","detail":"{\"A\":\"吃喝穿住\",\"B\":\"物质生活资料的生产\",\"C\":\"人的自觉意识活动\",\"D\":\"结成社会关系\"}","difficult":"中","type":"single","chapter":"b2f7442d-f018-4535-bced-bcd48b6021fb"},{"id":"23357ee935958fd58da395c705a5177c","title":" 劳动作为一个完整的过程（ ）。","detail":"{\"A\":\"只是自然过程\",\"B\":\"只是社会过程\",\"C\":\"仅具有抽象的一般性质\",\"D\":\"是劳动的一般性质和劳动的社会形式的统一\"}","difficult":"易","type":"single","chapter":"b2f7442d-f018-4535-bced-bcd48b6021fb"},{"id":"351df1b18b10872a00550bf761197703","title":"划分经济时代和衡量人类控制自然能力并反映社会生产力发展水平的标志是(     )","detail":"{\"A\":\"人的劳动\",\"B\":\"劳动对象\",\"C\":\"生产工具\",\"D\":\"生产资料\"}","difficult":"易","type":"single","chapter":"b2f7442d-f018-4535-bced-bcd48b6021fb"},{"id":"723bfef67bdfdfc61d8f37b0d2b5f939","title":"我国以公有制为主体，多种所有制经济共同发展的基本经济制度是由于（ ）决定的","detail":"{\"A\":\"我国现阶段生产力状况\",\"B\":\"我国社会主义制度的优越性\",\"C\":\"党的发展经济的政策\",\"D\":\"我国社会基本矛盾\"}","difficult":"易","type":"single","chapter":"b2f7442d-f018-4535-bced-bcd48b6021fb"},{"id":"a696533b35af0dc24c622fd507365059","title":" 阶级斗争的根源在于( )","detail":"{\"A\":\"社会政治格局的改变\",\"B\":\"各种政治主张的对立\",\"C\":\"各阶级之间物质利益的根本对立\",\"D\":\"思想和道德观念的根本对立\"}","difficult":"易","type":"single","chapter":"b2f7442d-f018-4535-bced-bcd48b6021fb"},{"id":"b50a64bfa6976052aed2e6cdf3062348","title":"进入汽车修配厂修理的汽车是 ( )","detail":"{\"A\":\"运输工具\",\"B\":\"劳动对象\",\"C\":\"劳动资料\",\"D\":\"生产要素\"}","difficult":"易","type":"single","chapter":"b2f7442d-f018-4535-bced-bcd48b6021fb"},{"id":"c74cfcd12d50c42be7cda6214d8750d3","title":" 著名现代德国思想家马克斯•韦伯在《新教伦理与资本主义精神》等著作中指出,民众的精神价值取向和社会风俗等会深刻地影响到社会的经济发展。这在哲学上的解释是(  )。","detail":"{\"A\":\"社会意识对社会存在具有决定作用\",\"B\":\"社会意识能反作用于社会存在\",\"C\":\"社会心理可以左右社会的发展\",\"D\":\"人们的精神世界决定了人们的物质生活\"}","difficult":"易","type":"single","chapter":"b2f7442d-f018-4535-bced-bcd48b6021fb"},{"id":"a88e527be2c40756595cb95a583bad7a","title":"在劳动资料这一复杂而广泛的物质系统中具有决定意义的因素是（ ）","detail":"{\"A\":\"信息传递系统\",\"B\":\"生产工具系统\",\"C\":\"动力系统\",\"D\":\"能源系统\"}","difficult":"难","type":"single","chapter":"b2f7442d-f018-4535-bced-bcd48b6021fb"},{"id":"2df323043aafce40e595bae1e478a8bf","title":"哲学上物质范畴与自然科学上的物质形态的关系是（ ）。","detail":"{\"A\":\"本源和派生的关系\",\"B\":\"一般和特殊的关系\",\"C\":\"本质和现象的关系\",\"D\":\"形式和内容的关系\"}","difficult":"易","type":"single","chapter":"e67f971e-8d43-4ee2-acf1-30ee30aa0119"},{"id":"5395ab4560e8ec119426acb5423d82b8","title":"物质运动的存在方式是（ ）。","detail":"{\"A\":\"时间和空间\",\"B\":\"时间\",\"C\":\"空间\",\"D\":\"一个位置到另一个位置\"}","difficult":"易","type":"single","chapter":"e67f971e-8d43-4ee2-acf1-30ee30aa0119"},{"id":"accc833702e567dc7def0dee033bd195","title":"意识产生的决定性环节是：（ ）。","detail":"{\"A\":\"人脑的进化\",\"B\":\"动物心理的形成\",\"C\":\"语言的产生\",\"D\":\"劳动\"}","difficult":"易","type":"single","chapter":"e67f971e-8d43-4ee2-acf1-30ee30aa0119"},{"id":"afb47f08127847a30ec59b04d4c25353","title":"新事物是指（ ）。","detail":"{\"A\":\"符合事物发展规律的事物\",\"B\":\"在时间上先出现的事物\",\"C\":\"具有新特点的事物\",\"D\":\"比较完善的事物\"}","difficult":"易","type":"single","chapter":"e67f971e-8d43-4ee2-acf1-30ee30aa0119"},{"id":"85a25bec1c613efa193d2f877a8c2a7e","title":"“否定之否定仿佛是向肯定的回复”，这种观点是：（ ）。","detail":"{\"A\":\"折衷主义的观点\",\"B\":\"辩证法的观点\",\"C\":\"诡辩论的观点\",\"D\":\"形而上学的观点\"}","difficult":"中","type":"single","chapter":"e67f971e-8d43-4ee2-acf1-30ee30aa0119"},{"id":"b570a280f48dfd67dc1b179a706a9d3d","title":"科学家洛伦兹提出“蝴蝶效应”理论称：“可预言：一只蝴蝶在巴西震动翅膀会在德克萨斯州掀起龙卷风”，这个说法（ ）。","detail":"{\"A\":\"说明一种事物或现象可以通过一系列中介环节和另一事物、现象发生联系\",\"B\":\"片面夸大了联系的普遍性\",\"C\":\"否认了联系的多样性\",\"D\":\"把联系理解为主观随意的，否认联系的客观性\"}","difficult":"中","type":"single","chapter":"e67f971e-8d43-4ee2-acf1-30ee30aa0119"},{"id":"c91480b00f029e594b0b6629d2b7d5c9","title":"“质和事物的存在是直接同一的”，是指：（ ）。","detail":"{\"A\":\"有质的事物和无质的事物存在着根本区别\",\"B\":\"任何事物都有质，任何质都属于一定事物\",\"C\":\"任何事物都是永远存在的，质也是永远不变的\",\"D\":\"事物的质是客观的，属性是主观的\"}","difficult":"中","type":"single","chapter":"e67f971e-8d43-4ee2-acf1-30ee30aa0119"},{"id":"dbec1fc268818914c9774d820f4dd7f8","title":"事物自我发展、自我完善的根据在于：（ ）。","detail":"{\"A\":\"事物的普遍联系\",\"B\":\"仿佛是“回到出发点的运动”\",\"C\":\"矛盾所固有的斗争性\",\"D\":\"事物内部的矛盾性\"}","difficult":"中","type":"single","chapter":"e67f971e-8d43-4ee2-acf1-30ee30aa0119"},{"id":"4c8ea08224e176576f6a2f3fbae128f3","title":"商品经济发展经历的两个阶段是：（    ）","detail":"{\"A\":\"脑力商品经济和体力商品经济\",\"B\":\"一般商品经济和复杂商品经济\",\"C\":\"简单商品经济和复杂商品经济\",\"D\":\"简单商品经济和发达商品经济\"}","difficult":"中","type":"single","chapter":"c6b67cc9-950a-43a5-9643-80a16fbe6b09"},{"id":"8a919684414f5db5e9b9128d36b2f0c1","title":"劳动力商品与其他商品不同的最根本特征是（  ）","detail":"{\"A\":\"劳动力存在于人的身体之内\",\"B\":\"劳动力在一定条件下可以转化为商品\",\"C\":\"劳动力使用价值是价值的源泉\",\"D\":\"、劳动力价值受历史道德因素影响\"}","difficult":"中","type":"single","chapter":"c6b67cc9-950a-43a5-9643-80a16fbe6b09"},{"id":"057c0788a1b3202878196e7244c3e29e","title":" 某工厂原工作日为8小时，必要劳动时间和剩余劳动时间各为4小时，若分别采用绝对剩余价值和相对剩余价值两种生产方法，各增加剩余劳动时间2小时，它们的剩余价值率分别为（     ）","detail":"{\"A\":\"150％，100％\",\"B\":\"150％，300％\",\"C\":\"100％，200％\",\"D\":\"150％，200％\"}","difficult":"难","type":"single","chapter":"c6b67cc9-950a-43a5-9643-80a16fbe6b09"},{"id":"e94fd08179e2762a318546206d5532c5","title":"在资本主义市场上，商品出售价格的最低界限是（  ）","detail":"{\"A\":\"商品的个别价值\",\"B\":\"商品的社会价值\",\"C\":\"商品的生产成本\",\"D\":\"商品的生产价格\"}","difficult":"难","type":"single","chapter":"c6b67cc9-950a-43a5-9643-80a16fbe6b09"},{"id":"1d4466afa9bb8b867ba1917b239dea91","title":"劳动生产率越高，同一劳动在同一时期内生产的产品数量越多，则其创造的价值总量 (  )","detail":"{\"A\":\"越多\",\"B\":\"越少\",\"C\":\"不变\",\"D\":\"无法确定\"}","difficult":"易","type":"single","chapter":"c6b67cc9-950a-43a5-9643-80a16fbe6b09"},{"id":"be946ca83d4248071fce24a02f01e5f7","title":" 资本主义相对过剩人口的产生是（ ）","detail":"{\"A\":\"人口繁殖过多过快的结果\",\"B\":\"工业吸收的人口绝对减少的结果\",\"C\":\"资本有机构成不变条件下资本积累的结果\",\"D\":\"资本有机构成不断提高条件下资本积累的结果\"}","difficult":"易","type":"single","chapter":"c6b67cc9-950a-43a5-9643-80a16fbe6b09"},{"id":"f6126d461f3c2fc05694e23224f260d6","title":"马克思划分不变资本和可变资本的根据是（   ）   ","detail":"{\"A\":\"在剩余价值生产中的作用不同\",\"B\":\"价值周转方式不同\",\"C\":\"存在的物质形态不同\",\"D\":\"在循环中的职能不同\"}","difficult":"易","type":"single","chapter":"c6b67cc9-950a-43a5-9643-80a16fbe6b09"},{"id":"fedeab85b13f0134cdd83e3299a89bb5","title":"商品经济是通过商品货币关系实行等价交换的经济形式，它的基本规律是（  ）","detail":"{\"A\":\"价值规律\",\"B\":\"剩余价值规律\",\"C\":\"竞争规律\",\"D\":\"货币流通规律\"}","difficult":"易","type":"single","chapter":"c6b67cc9-950a-43a5-9643-80a16fbe6b09"},{"id":"7274c8584bf4c1533b2cd758adaa4e1a","title":"真理是指（  ） ","detail":"{\"A\":\"客观事物及其规律性\",\"B\":\"人们对客观事物及其规律性的正确认识\",\"C\":\"对人们有用、能满足人们需要的理论\",\"D\":\"先进阶级的进步认识\"}","difficult":"中","type":"single","chapter":"30eeedcc-48cd-4c0d-acb8-c392443ad937"},{"id":"cf61e16bf4a75a44b567b584b4424b9e","title":"“进行社会主义现代化建设必须尊重知识，尊重人才。”这一思想体现的辩证唯物主义认识论的原理是（ ）","detail":"{\"A\":\"理性认识依赖于感性认识\",\"B\":\"科学理论对实践有指导作用\",\"C\":\"理论来源于实践\",\"D\":\"认识具有反复性、无限性、上升性\"}","difficult":"中","type":"single","chapter":"30eeedcc-48cd-4c0d-acb8-c392443ad937"},{"id":"f81a76cf48d140432a59dc62e46e9118","title":"对一个复杂事物的正确认识往往需要经过（  ） ","detail":"{\"A\":\"由感性认识到理性认识，再由理性认识回到感性认识\",\"B\":\"由感性认识到理性认识，再由理性认识回到实践的两次飞跃\",\"C\":\"由实践到认识，由认识到实践的一次完成\",\"D\":\"由实践到认识，由认识到实践的多次反复\"}","difficult":"中","type":"single","chapter":"30eeedcc-48cd-4c0d-acb8-c392443ad937"},{"id":"95fe8c9b936e8d5b608e1c34a66a68d9","title":"“真理和谬误的对立，只是在非常有限的范围内才有意义”是（ ）","detail":"{\"A\":\"形而上学的观点\",\"B\":\"唯物辩证法的观点\",\"C\":\"诡辩论的观点\",\"D\":\"相对主义的观点\"}","difficult":"易","type":"single","chapter":"30eeedcc-48cd-4c0d-acb8-c392443ad937"},{"id":"9b1720de25e4c044c27ab36eb39c27d3","title":"人的价值的两个方面是指( )  ","detail":"{\"A\":\"物质价值和精神价值\",\"B\":\"政治价值和经济价值\",\"C\":\"社会价值和自我价值\",\"D\":\"潜在价值和现实价值\"}","difficult":"易","type":"single","chapter":"30eeedcc-48cd-4c0d-acb8-c392443ad937"},{"id":"9423898bb3d962ff7fea07b4845e4c8c","title":"一个完整的认识过程需要经过两次飞跃，下列选项中属于第二次飞跃的是：( )","detail":"{\"A\":\"调查研究，了解情况\",\"B\":\"深入思考，形成理论\",\"C\":\"精心安排，制定计划\",\"D\":\"执行计划，付诸实践\"}","difficult":"难","type":"single","chapter":"30eeedcc-48cd-4c0d-acb8-c392443ad937"},{"id":"dadbb3a4fe4bf45a905f3a8ae2bd30d3","title":"恩格斯说：“人的智力是指人如何学会改造自然界而发展的”，这句话说明(   )","detail":"{\"A\":\"人具有改造世界的能力\",\"B\":\"人的认识具有主观能动性\",\"C\":\"人的认识能力是不受限制的\",\"D\":\"实践是认识发展的动力\"}","difficult":"难","type":"single","chapter":"30eeedcc-48cd-4c0d-acb8-c392443ad937"},{"id":"ed989f627b08d29d3c7e6d4ad98161ff","title":"在认识过程的第二次飞跃中的认识是(   )","detail":"{\"A\":\"感性具体阶段的认识\",\"B\":\"理性抽象阶段的认识\",\"C\":\"理性具体阶段的认识\",\"D\":\"感性与理性统一的认识\"}","difficult":"难","type":"single","chapter":"30eeedcc-48cd-4c0d-acb8-c392443ad937"},{"id":"2a65d59401dd6abd431d3c91b08dc08a","title":"无产阶级政党的组织原则是(  )","detail":"{\"A\":\"集体领导\",\"B\":\"理论联系实际\",\"C\":\"实事求是\",\"D\":\"民主集中制\"}","difficult":"易","type":"single","chapter":"684a7593-74e4-4d89-a272-a0a1c1fedd0e"},{"id":"35f46f595dee48ed45801c56eefb4dcd","title":"社会主义政治制度的基本特征是(  )","detail":"{\"A\":\"坚持社会主义方向\",\"B\":\"无产阶级政党的领导\",\"C\":\"无产阶级专政的政权\",\"D\":\"马克思主义的指导\"}","difficult":"易","type":"single","chapter":"684a7593-74e4-4d89-a272-a0a1c1fedd0e"},{"id":"6db38e714e620d7a6db8503c4ff3188e","title":"国际共产主义运动的历史表明,社会主义的发展道路不是单一性的,而是(    )的。 ","detail":"{\"A\":\"多样性\",\"B\":\"全面性\",\"C\":\"整体性\",\"D\":\"阶段性\"}","difficult":"易","type":"single","chapter":"684a7593-74e4-4d89-a272-a0a1c1fedd0e"},{"id":"24edb37ec912ee05224b7af71e30291e","title":"列宁对关于无产阶级社会主义革命学说的重大贡献是（  ) ","detail":"{\"A\":\"提出了战时共产主义政策\",\"B\":\"提出了新经济政策\",\"C\":\"提出了社会主义革命将首先在一国或数国取得胜利的理论\",\"D\":\"提出了利用国家资本主义过渡社会主义的理论\"}","difficult":"难","type":"single","chapter":"684a7593-74e4-4d89-a272-a0a1c1fedd0e"},{"id":"871ed290d51f2322d39579fa0ba17f9f","title":"世界上第一个无产阶级政党是（　）","detail":"{\"A\":\"布尔什维克\",\"B\":\"中国共产党\",\"C\":\"共产主义者同盟\",\"D\":\"德国社会民主工党\"}","difficult":"难","type":"single","chapter":"684a7593-74e4-4d89-a272-a0a1c1fedd0e"},{"id":"25c9d7091cc17b0ed00cc53b1fdc47e9","title":"无产阶级最终实现自身获得解放只有 (    )","detail":"{\"A\":\"打碎旧的国家机器\",\"B\":\"建立社会公有制\",\"C\":\"提高劳动生产率\",\"D\":\"解放全人类\"}","difficult":"中","type":"single","chapter":"684a7593-74e4-4d89-a272-a0a1c1fedd0e"},{"id":"5375bfb2da050db0daf1f692f43d37c3","title":"民主的根本性质最终取决于(     )","detail":"{\"A\":\"由谁来进行统治\",\"B\":\"其经济基础的性质\",\"C\":\"统治阶级如何来进行统治\",\"D\":\"是不是全民的民主\"}","difficult":"中","type":"single","chapter":"684a7593-74e4-4d89-a272-a0a1c1fedd0e"},{"id":"707366af8c5c007d3b517fa6cb1533f8","title":"(  )是指无产阶级以夺取政权为目的的斗争,它是无产阶级反对整个资产阶级的斗争形式。 ","detail":"{\"A\":\"政治斗争\",\"B\":\"文化斗争\",\"C\":\"思想斗争\",\"D\":\"经济斗争\"}","difficult":"中","type":"single","chapter":"684a7593-74e4-4d89-a272-a0a1c1fedd0e"},{"id":"c2dc2f726b281369c74224eedd5270c9","title":"采用“通过批判旧世界来发现新世界”方法的是（  ）","detail":"{\"A\":\"空想社会主义者\",\"B\":\"马克思主义\",\"C\":\"唯物主义\",\"D\":\"唯心主义\"}","difficult":"难","type":"single","chapter":"60b92b95-8392-4eae-93ec-d774d90701d7"},{"id":"2480e40c83316f6fce10392c7d460662","title":"必然王国和自由王国是社会发展的（ ）","detail":"{\"A\":\"两种不同的状态\",\"B\":\"两种不同的选择\",\"C\":\"两种不同的道路\",\"D\":\"两种不同的理想\"}","difficult":"中","type":"single","chapter":"60b92b95-8392-4eae-93ec-d774d90701d7"},{"id":"5a9a6f5fd5916ac9f39100338b89137a","title":"“代替那存在着阶级和阶级对立的资产阶级旧社会的，将是这样一个联合体，在那里，每个人的自由发展是一切人的自由发展的条件”。这一段话出现在（ ）","detail":"{\"A\":\"《资本论》中\",\"B\":\"《共产主义原理》中\",\"C\":\"《哥达纲领批判》中\",\"D\":\"《共产党宣言》中\"}","difficult":"中","type":"single","chapter":"60b92b95-8392-4eae-93ec-d774d90701d7"},{"id":"b20b2beeca668a3569cb3cba167ebf8d","title":"自由王国是指人们（ ）","detail":"{\"A\":\"处于绝对自由的原始社会状态\",\"B\":\"不再受自然规律和社会规律支配的状态\",\"C\":\"允许自由竞争的资本主义状态\",\"D\":\"摆脱了自然和社会关系的奴役，成为自己社会关系主人的状态\"}","difficult":"中","type":"single","chapter":"60b92b95-8392-4eae-93ec-d774d90701d7"},{"id":"cb325bccfa862bb42b981ce93ccc1c77","title":"“物的依赖性关系”是（    ) ","detail":"{\"A\":\"资本主义社会以前的人与人之间的关系\",\"B\":\"资本主义社会之中的人与人之间的关系\",\"C\":\"社会主义社会之中的人与人之间的关系\",\"D\":\"共产主义社会之中的人与人之间的关系\"}","difficult":"中","type":"single","chapter":"60b92b95-8392-4eae-93ec-d774d90701d7"},{"id":"4b7db0a6a9b261545a234b63594f7944","title":"自觉运用预见未来社会的方法论原则,是我们展望未来理想社会的基本依据,这些原则包括 (     )。①在揭示人类社会发展一般规律的基础上指明社会发展的方向 \n②在剖析资本主义旧世界的过程中阐发未来新世界的特点 \n    ③在社会主义社会发展中不断深化对未来共产主义社会的认识 \n    ④立足于揭示未来社会的一般特征,对各种细节作具体描绘 \n ","detail":"{\"A\":\"①②③\",\"B\":\"②③④\",\"C\":\"①③④\",\"D\":\"①②③④\"}","difficult":"易","type":"single","chapter":"60b92b95-8392-4eae-93ec-d774d90701d7"},{"id":"941c945b35c0fba72135f7199bba40f8","title":"在展望未来社会的问题上，马克思主义与空想社会主义的根本区别是（ ）","detail":"{\"A\":\"展望的内容是否正确\",\"B\":\"展望的目的和动机是否正确\",\"C\":\"有没有预见性\",\"D\":\"立场、观点和方法是否科学\"}","difficult":"易","type":"single","chapter":"60b92b95-8392-4eae-93ec-d774d90701d7"},{"id":"e338ea696e75d82996caea4db4fa5d14","title":"共产主义理想的实现要靠（   ） ","detail":"{\"A\":\"神秘力量\",\"B\":\"奇迹\",\"C\":\"人民的实践、社会的进步和发展\",\"D\":\"科学\"}","difficult":"易","type":"single","chapter":"60b92b95-8392-4eae-93ec-d774d90701d7"},{"id":"197e94c9cf8051a7e019a11a4e47755c","title":"资本主义由自由竞争阶段进入垄断阶段，最根本的标志在于(   )","detail":"{\"A\":\"垄断代替自由竞争在经济生活中占统治地位\",\"B\":\"资本输出代替商品输出在经济生活中占统治地位\",\"C\":\"银行资本代替工业资本在经济生活中占统治地位\",\"D\":\"国家垄断代替私人垄断在经济生活中占统治地位\"}","difficult":"易","type":"single","chapter":"b0ce731e-024f-4743-98f2-aedf83fdfa91"},{"id":"28515624566d32ece4b95f07d692e8cc","title":"国家垄断资本主义是(   )","detail":"{\"A\":\"消除生产无政府状态的垄断资本主义\",\"B\":\"资产阶级国家同垄断资本相互分离的垄断资本主义\",\"C\":\"资产阶级国家同垄断资本融合在一起的垄断资本主义\",\"D\":\"带有社会主义因素的垄断资本主义\"}","difficult":"易","type":"single","chapter":"b0ce731e-024f-4743-98f2-aedf83fdfa91"},{"id":"47fe59d649ed4901c759bb1187777d9a","title":"当代资本主义的新变化 (     )。 ","detail":"{\"A\":\"意味着资本主义生产关系的根本性质发生了变化\",\"B\":\"从根本上改变了资本主义社会\",\"C\":\"从根本上适应了生产的社会化\",\"D\":\"从根本上说是人类社会发展一般规律作用的结果\"}","difficult":"易","type":"single","chapter":"b0ce731e-024f-4743-98f2-aedf83fdfa91"},{"id":"6b3bf0e42ff6385baf7b2184b05816de","title":"垄断利润的获得，主要是通过（  ）","detail":"{\"A\":\"垄断价格实现的\",\"B\":\"自由竞争实现的\",\"C\":\"市场调节实现的\",\"D\":\"行政干预实现的\"}","difficult":"易","type":"single","chapter":"b0ce731e-024f-4743-98f2-aedf83fdfa91"}],"multi":[{"id":"740711306600bd0134b760e2ce75c6ba","title":"经济基础对上层建筑的决定作用，主要表现在（ ）","detail":"{\"A\":\"经济基础决定上层建筑的生产、变化与发展\",\"B\":\"经济基础决定上层建筑的性质\",\"C\":\"经济基础决定上层建筑是否具有反作用\",\"D\":\"经济基础决定上层建筑是否包括自然科学\"}","difficult":"易","type":"multi","chapter":"b2f7442d-f018-4535-bced-bcd48b6021fb"},{"id":"dc03257627d9424bf01dd02cd358132f","title":"在把生产力发展作为评价社会进步的标准时，不能忽视 ( ) ","detail":"{\"A\":\"评价社会进步的其他标准\",\"B\":\"地理环境在社会发展中的作用\",\"C\":\"人口因素在社会发展中的作用\",\"D\":\"国际环境的影响在社会发展中的作用\"}","difficult":"易","type":"multi","chapter":"b2f7442d-f018-4535-bced-bcd48b6021fb"},{"id":"247f6631fcaad873f208f73303a0b617","title":"历史观中唯意志论的错误在于把人类历史看作是（ ）","detail":"{\"A\":\"由人的意志决定的\",\"B\":\"不由人的意志决定的\",\"C\":\"人的意志可任意改变的\",\"D\":\"客观精神的进程\"}","difficult":"中","type":"multi","chapter":"b2f7442d-f018-4535-bced-bcd48b6021fb"},{"id":"b12bdfe40e4c3194bbb60f9223c1b05e","title":"“要正确处理好投资和消费、内需和外需的关系，最根本的是扩大国内消费需求。”这句话体现的哲理是（ ）。","detail":"{\"A\":\"内因是事物变化发展的根据\",\"B\":\"量变与质变的辩证关系\",\"C\":\"两点论与重点论的统一\",\"D\":\"整体与部分的辩证关系\"}","difficult":"中","type":"multi","chapter":"e67f971e-8d43-4ee2-acf1-30ee30aa0119"},{"id":"8f271f4113c6a8efc249a2bd25d55d8f","title":"唯物辩证法与形而上学的对立表现在：( ) 。","detail":"{\"A\":\"联系的观点与孤立的观点\",\"B\":\"发展的观点与静止的观点\",\"C\":\"承认规律的客观性与承认规律的主观性\",\"D\":\"世界本原问题\"}","difficult":"易","type":"multi","chapter":"e67f971e-8d43-4ee2-acf1-30ee30aa0119"},{"id":"ec2be6ea5f381a1be1ae57af628003b1","title":"“我们今天生活着的世界，与其说是自然世界，还不如说是人造或人为世界。在我们的周围几乎每样东西都刻有人的技能的痕迹。”这段话应理解为：（ ）。","detail":"{\"A\":\"人造的或认为的世界是惟一存在的世界\",\"B\":\"人类世界是人的实践活动对象化的结果\",\"C\":\"自在世界日益转化为人化自然\",\"D\":\"现实世界是人类精神的创造物\"}","difficult":"难","type":"multi","chapter":"e67f971e-8d43-4ee2-acf1-30ee30aa0119"},{"id":"af9c1bdd34d27209278a640dd8927d78","title":"资本主义国家与垄断资本相结合的主要形式有（ ）","detail":"{\"A\":\"有限责任公司\",\"B\":\"股份公司\",\"C\":\"国有经济\",\"D\":\"国有资本和私人资本在企业内部结合\"}","difficult":"易","type":"multi","chapter":"b0ce731e-024f-4743-98f2-aedf83fdfa91"},{"id":"cc7de0a613a8ddb00e241bb1acc73e6f","title":"资产阶级意识形态的本质是(    )","detail":"{\"A\":\"在一定程度上代表了人民的意志和愿望\",\"B\":\"集中地体现了资本主义国家文化的精华\",\"C\":\"为资本主义社会形态的经济基础服务的\",\"D\":\"资产阶级阶级意识的集中体现\"}","difficult":"易","type":"multi","chapter":"b0ce731e-024f-4743-98f2-aedf83fdfa91"},{"id":"f5784ab19ae860c8a29a85325a4d2116","title":"迄今为止资本主义社会的发展，大体可分为（  ）","detail":"{\"A\":\"自由竞争资本主义和垄断资本主义两个阶段\",\"B\":\"垄断资本主义和非垄断资本主义两个阶段\",\"C\":\"商品经济和市场经济两个阶段\",\"D\":\"国内垄断和国际垄断两个阶段\"}","difficult":"易","type":"multi","chapter":"b0ce731e-024f-4743-98f2-aedf83fdfa91"},{"id":"4650fccc999d9440a5b262329a20753a","title":"  固定资本更新是指(   )","detail":"{\"A\":\"所有生产资料的更新\",\"B\":\"厂房、机器、设备的更新\",\"C\":\"原料、燃料、辅助材料的更新\",\"D\":\"劳动力的更新\"}","difficult":"难","type":"multi","chapter":"c6b67cc9-950a-43a5-9643-80a16fbe6b09"},{"id":"3f93c2930d6dd2a3ac8b4e61c2ed2ecf","title":"在商品价值的形式发展中一切商品的价值通过贵金属表现出来的价值形式是: （）","detail":"{\"A\":\"简单价值形式\",\"B\":\"扩大价值形式\",\"C\":\"一般价值形式\",\"D\":\"货币形式\"}","difficult":"中","type":"multi","chapter":"c6b67cc9-950a-43a5-9643-80a16fbe6b09"},{"id":"f91a08613ee5ad2ea719d03433afbe4a","title":"反映资本家对工人的剥削程度的公式是(  )  ","detail":"{\"A\":\"剩余价值/可变成本\",\"B\":\"剩余价值/全部预付资本\",\"C\":\"剩余劳动时间/必要劳动时间\",\"D\":\"年剩余价值量/预付可变资本\"}","difficult":"中","type":"multi","chapter":"c6b67cc9-950a-43a5-9643-80a16fbe6b09"},{"id":"b456ca5b1565ff7d757d501d8ed48486","title":"(   )是指无产阶级在意识形态领域里同反马克思主义进行的斗争。","detail":"{\"A\":\"政治斗争\",\"B\":\"文化斗争\",\"C\":\"思想斗争\",\"D\":\"经济斗争\"}","difficult":"中","type":"multi","chapter":"684a7593-74e4-4d89-a272-a0a1c1fedd0e"},{"id":"fe6bfa75e6047e489a8f37d4162a2941","title":"社会主义社会的主要特征不包括（）","detail":"{\"A\":\"剥削制度的消灭和在生产资料所有制上坚持以公有制为主体\",\"B\":\"按需分配\",\"C\":\"大力发展社会主义市场经济\",\"D\":\"实行无政府主义\"}","difficult":"中","type":"multi","chapter":"684a7593-74e4-4d89-a272-a0a1c1fedd0e"},{"id":"4337eac9e224d6a3f2552541623318d1","title":"在新经济政策时期,苏维埃俄国所作的努力包括(   )。 ","detail":"{\"A\":\"恢复和发展商品经济\",\"B\":\"在农村变余粮征集制为农产品收购制\",\"C\":\"废除商品货币关系\",\"D\":\"建立和发展计划经济体制\"}","difficult":"易","type":"multi","chapter":"684a7593-74e4-4d89-a272-a0a1c1fedd0e"},{"id":"20ed7c21ffdcabe0af23066366be478f","title":"人类对自然界的认识是一个长期的探索过程，在这个过程中，对自然界认识的深度和广度主要是与：()","detail":"{\"A\":\"社会实践水平相联系\",\"B\":\"地理环境相联系\",\"C\":\"人口因素相联系\",\"D\":\"哲学发展水平相联系\"}","difficult":"易","type":"multi","chapter":"30eeedcc-48cd-4c0d-acb8-c392443ad937"},{"id":"2a9597badf8903431028472fa76da5b5","title":"对于同一棵大树，在木匠眼中是木材，画家看到的是色彩和色调，植物学家看到的是它的形态特征，这是由于：( )","detail":"{\"A\":\"人的感觉受理性指导\",\"B\":\"理性认识是感性认识的基础\",\"C\":\"已有的认识影响感觉活动\",\"D\":\"意识建构认识对象\"}","difficult":"易","type":"multi","chapter":"30eeedcc-48cd-4c0d-acb8-c392443ad937"},{"id":"65a01c259ba121f6da67e84522c27527","title":"认识的客体指的是（  ）","detail":"{\"A\":\"客观存在的一切事物\",\"B\":\"自然界存在的事物\",\"C\":\"自然界和社会中的事物\",\"D\":\"成为主体认识对象和实践对象的事物\"}","difficult":"中","type":"multi","chapter":"30eeedcc-48cd-4c0d-acb8-c392443ad937"},{"id":"1ef200c989f2e05a03fe17bf6c5574e3","title":"马克思主义产生的直接理论渊源是（ ）和法国英国的空想社会主义。 ","detail":"{\"A\":\"德国古典哲学\",\"B\":\"英国古典政治经济学\",\"C\":\"文艺复兴运动\",\"D\":\"法国启蒙思想\"}","difficult":"易","type":"multi","chapter":"c32b6b23-286f-41c8-a871-9e6fa875baba"},{"id":"e3cec8078de245dde53cda12a9759c35","title":"我们可以从不同的角度理解马克思主义，包括：（ ）。","detail":"{\"A\":\"从创始者的认识成果讲，是马克思恩格斯创立的基本理论、基本观点、基本方法\",\"B\":\"从阶级属性讲，是无产阶级争取自身解放和整个人类解放的科学理论\",\"C\":\"从研究对象和主要内容讲，是资产阶级的世界观和方法论\",\"D\":\"从主要构成讲，包括唯物论和辩证法\"}","difficult":"易","type":"multi","chapter":"c32b6b23-286f-41c8-a871-9e6fa875baba"}]}}